pyAudioProcessing/__init__.py
pyAudioProcessing/clean.py
pyAudioProcessing/convert_audio.py
pyAudioProcessing/extract_features.py
pyAudioProcessing/plot.py
pyAudioProcessing/run_classification.py
pyAudioProcessing/utils.py
pyAudioProcessing/features/__init__.py
pyAudioProcessing/features/feature_computations.py
pyAudioProcessing/features/filters.py
pyAudioProcessing/features/getGfcc.py
pyAudioProcessing/features/mfcc.py
pyAudioProcessing/features/spectral.py
pyAudioProcessing/models/__init__.py
pyAudioProcessing/models/music genre/__init__.py
pyAudioProcessing/models/music genre/svm_clf
pyAudioProcessing/models/music genre/svm_clf.arff
pyAudioProcessing/models/music genre/svm_clfMEANS
pyAudioProcessing/models/speechVSmusic/__init__.py
pyAudioProcessing/models/speechVSmusic/svm_clf
pyAudioProcessing/models/speechVSmusic/svm_clf.arff
pyAudioProcessing/models/speechVSmusic/svm_clfMEANS
pyAudioProcessing/models/speechVSmusicVSbirds/__init__.py
pyAudioProcessing/models/speechVSmusicVSbirds/svm_clf
pyAudioProcessing/models/speechVSmusicVSbirds/svm_clf.arff
pyAudioProcessing/models/speechVSmusicVSbirds/svm_clfMEANS
pyAudioProcessing/trainer/__init__.py
pyAudioProcessing/trainer/audioTrainTest.py
pyAudioProcessing-1.1.13.data/data/requirements.txt
tests/__init__.py
tests/test_feature_extraction.py
tests/test_plot.py
pyAudioProcessing-1.1.13.dist-info/LICENSE.md
pyAudioProcessing-1.1.13.dist-info/METADATA
pyAudioProcessing-1.1.13.dist-info/WHEEL
pyAudioProcessing-1.1.13.dist-info/top_level.txt
pyAudioProcessing-1.1.13.dist-info/RECORD
