Metadata-Version: 2.1
Name: pyAudioProcessing
Version: 1.1.13
Summary: Audio processing-feature extraction and building machine learning models from audio data.
Home-page: https://github.com/jsingh811/pyAudioProcessing
Author: Jyotika Singh
Classifier: Programming Language :: Python :: 3
Classifier: License :: OSI Approved :: GNU General Public License v3 (GPLv3)
Classifier: Operating System :: OS Independent
Requires-Python: >=3.6, <4
License-File: LICENSE.md
Requires-Dist: matplotlib (==3.3.4)
Requires-Dist: scipy (==1.5.4)
Requires-Dist: pydub (==0.25.1)
Requires-Dist: ffmpeg (==1.4)
Requires-Dist: pytest (==6.2.3)
Requires-Dist: numpy (==1.19.5) ; python_version < "3.7"
Requires-Dist: scikit-learn (==0.24.2) ; python_version <= "3.7"
Requires-Dist: numpy (==1.21.6) ; python_version == "3.7"
Requires-Dist: numpy (==1.22.0) ; python_version >= "3.8"
Requires-Dist: scikit-learn (==1.1.1) ; python_version >= "3.8"
